poetrycurrenttime/__init__.py
poetrycurrenttime/main.py
poetrycurrenttime-0.1.0.dist-info/METADATA
poetrycurrenttime-0.1.0.dist-info/WHEEL
poetrycurrenttime-0.1.0.dist-info/RECORD
