Metadata-Version: 2.3
Name: poetrycurrenttime
Version: 0.1.0
Summary: 
Author: kaavyakaavya390
Author-email: kaavyakaavya390@gmail.com
Requires-Python: >=3.11
Classifier: Programming Language :: Python :: 3
Classifier: Programming Language :: Python :: 3.11
Classifier: Programming Language :: Python :: 3.12
Classifier: Programming Language :: Python :: 3.13
Requires-Dist: matplotlib (>=3.10.6,<4.0.0)
Requires-Dist: numpy (>=2.3.3,<3.0.0)
Requires-Dist: pandas (>=2.3.2,<3.0.0)
